placeholders/__init__.py
placeholders/controls.py
placeholders/tools.py
placeholders-2.2.data/scripts/placeholders
placeholders-2.2.dist-info/LICENSE
placeholders-2.2.dist-info/METADATA
placeholders-2.2.dist-info/WHEEL
placeholders-2.2.dist-info/top_level.txt
placeholders-2.2.dist-info/RECORD
