Metadata-Version: 2.1
Name: placeholders
Version: 2.2
Summary: Create placeholder images by embedding keywords into regular jpg images.
Home-page: https://github.com/austinbrown34/placeholders
Author: Austin Brown
Author-email: austinbrown34@gmail.com
Keywords: image,exif,jpg
License-File: LICENSE
Requires-Dist: piexif
Requires-Dist: Pillow
Requires-Dist: pydantic
Requires-Dist: PyYAML
